Metadata-Version: 2.1
Name: boompy
Version: 2.0.0
Summary: Simple command line snippets.
Home-page: https://github.com/epochblue/boom.py
Author: Bill Israel
Author-email: bill.israel@hey.com
Maintainer: Bill Israel
Maintainer-email: bill.israel@hey.com
License: MIT
Keywords: clipboard,boom,copy,paste,snippet
Platform: UNKNOWN
Classifier: Development Status :: 5 - Production/Stable
Classifier: Environment :: Console
Classifier: Environment :: MacOS X
Classifier: Environment :: Win32 (MS Windows)
Classifier: Intended Audience :: Developers
Classifier: Intended Audience :: Information Technology
Classifier: Intended Audience :: System Administrators
Classifier: License :: OSI Approved :: MIT License
Classifier: Operating System :: MacOS :: MacOS X
Classifier: Operating System :: Microsoft :: Windows
Classifier: Operating System :: POSIX :: Linux
Classifier: Programming Language :: Python :: 3
Classifier: Topic :: Utilities
Provides-Extra: dev
License-File: LICENSE
